pydicomext/__init__.py
pydicomext/_version.py
pydicomext/combineSeries.py
pydicomext/dicomDir.py
pydicomext/loadDirectory.py
pydicomext/merge.py
pydicomext/patient.py
pydicomext/series.py
pydicomext/sortSeries.py
pydicomext/study.py
pydicomext/util.py
pydicomext/volume.py
pydicomext-1.0.0.dist-info/LICENSE
pydicomext-1.0.0.dist-info/METADATA
pydicomext-1.0.0.dist-info/WHEEL
pydicomext-1.0.0.dist-info/top_level.txt
pydicomext-1.0.0.dist-info/RECORD
