Metadata-Version: 2.1
Name: pydicomext
Version: 1.0.0
Summary: Python package that provides additional features to pydicom
Home-page: https://github.com/addisonElliott/pydicomext
Author: Addison Elliott
Author-email: addison.elliott@gmail.com
License: MIT License
Project-URL: Documentation, https://github.com/addisonElliott/pydicomext
Project-URL: Source, https://github.com/addisonElliott/pydicomext
Project-URL: Tracker, https://github.com/addisonElliott/pydicomext/issues
Keywords: pydicom dicom load read save medical imaging
Platform: UNKNOWN
Classifier: Development Status :: 4 - Beta
Classifier: Topic :: Scientific/Engineering
Classifier: License :: OSI Approved :: MIT License
Classifier: Programming Language :: Python
Classifier: Programming Language :: Python :: 3
Classifier: Programming Language :: Python :: 3.4
Classifier: Programming Language :: Python :: 3.5
Classifier: Programming Language :: Python :: 3.6
Classifier: Programming Language :: Python :: 3.7
Classifier: Programming Language :: Python :: 3.8
Classifier: Operating System :: OS Independent
Requires-Python: >=3.4
Requires-Dist: numpy (>=1.12)
Requires-Dist: pydicom
